{
  "hash": "be3f941b",
  "configHash": "a3575868",
  "lockfileHash": "428152db",
  "browserHash": "37c08fa8",
  "optimized": {
    "react": {
      "src": "../../node_modules/react/index.js",
      "file": "react.js",
      "fileHash": "5845fb8e",
      "needsInterop": true
    },
    "react-dom/client": {
      "src": "../../node_modules/react-dom/client.js",
      "file": "react-dom_client.js",
      "fileHash": "d78848c7",
      "needsInterop": true
    }
  },
  "chunks": {
    "chunk-TDVGPZLM": {
      "file": "chunk-TDVGPZLM.js"
    }
  }
}